pytelecontrol/__init__.py
pytelecontrol/__main__.py
pytelecontrol-0.1.1.dist-info/LICENSE
pytelecontrol-0.1.1.dist-info/METADATA
pytelecontrol-0.1.1.dist-info/WHEEL
pytelecontrol-0.1.1.dist-info/RECORD
